ddb_exporter.py
ddb_exporter-0.1.0.dist-info/entry_points.txt
ddb_exporter-0.1.0.dist-info/LICENSE
ddb_exporter-0.1.0.dist-info/METADATA
ddb_exporter-0.1.0.dist-info/WHEEL
ddb_exporter-0.1.0.dist-info/RECORD
