Metadata-Version: 2.1
Name: ddb-exporter
Version: 0.1.0
Summary: 
License: MIT
Author: tokoi
Author-email: tokoi@crandim.co.jp
Requires-Python: >=3.12,<4.0
Classifier: License :: OSI Approved :: MIT License
Classifier: Programming Language :: Python :: 3
Requires-Dist: boto3 (>=1.34.121,<2.0.0)
Requires-Dist: click (>=8.1.7,<9.0.0)
